besapi/__init__.py
besapi/__main__.py
besapi/besapi.py
besapi/plugin_utilities.py
besapi/plugin_utilities_win.py
besapi/schemas/BES.xsd
besapi/schemas/BESAPI.xsd
besapi/schemas/BESActionSettings.xsd
besapi-4.0.2.dist-info/licenses/LICENSE.txt
bescli/__init__.py
bescli/__main__.py
bescli/bescli.py
besapi-4.0.2.dist-info/METADATA
besapi-4.0.2.dist-info/WHEEL
besapi-4.0.2.dist-info/top_level.txt
besapi-4.0.2.dist-info/RECORD
