Metadata-Version: 2.4
Name: besapi
Version: 4.0.2
Summary: Library for working with the BigFix REST API
Home-page: https://github.com/jgstew/besapi
Author: Matt Hansen, James Stewart
Author-email: hansen.m@psu.edu, james@jgstew.com
Maintainer: James Stewart
Maintainer-email: james@jgstew.com
License: MIT
Keywords: bigfix iem tem rest api
Classifier: Programming Language :: Python :: 3
Classifier: Programming Language :: Python :: 3.9
Classifier: Operating System :: OS Independent
Classifier: License :: OSI Approved :: MIT License
Classifier: Development Status :: 5 - Production/Stable
Classifier: Intended Audience :: Developers
Classifier: Topic :: Software Development :: Libraries :: Python Modules
Classifier: Topic :: System :: Systems Administration
Requires-Python: >=3.9
License-File: LICENSE.txt
Requires-Dist: cmd2
Requires-Dist: lxml
Requires-Dist: requests
Requires-Dist: setuptools
Requires-Dist: pywin32; platform_system == "Windows"
Requires-Dist: urllib3>=2.2.3
Dynamic: license-file
